main.py
setup.py
byte_flux_3822a6dd00d6414daba3ae0de3930a5a.egg-info/PKG-INFO
byte_flux_3822a6dd00d6414daba3ae0de3930a5a.egg-info/SOURCES.txt
byte_flux_3822a6dd00d6414daba3ae0de3930a5a.egg-info/dependency_links.txt
byte_flux_3822a6dd00d6414daba3ae0de3930a5a.egg-info/requires.txt
byte_flux_3822a6dd00d6414daba3ae0de3930a5a.egg-info/top_level.txt