Metadata-Version: 2.1
Name: byte-flux_3822a6dd00d6414daba3ae0de3930a5a
Version: 9.6
Summary: anon
Author: anon
Author-email: xxx@outlook.com
Requires-Dist: requests
Requires-Dist: psutil
